{
  "page": "Slay_the_Spire_2:Neow's Talisman",
  "short_name": "Neow's Talisman",
  "summary": "At the start of the run, can be offered by .",
  "sections": {},
  "display_title": "<span class=\"mw-page-title-namespace\">Slay the Spire 2</span><span class=\"mw-page-title-separator\">:</span><span class=\"mw-page-title-main\">Neow&#039;s Talisman</span>",
  "fetched_at": "2026-05-20T06:21:08Z",
  "wikitext_chars": 426,
  "wikitext": "{{Relic Infobox|Neow's Talisman|2}}\n{{R|Neow's Talisman||2}} is an {{QueryLink|Relics|rarity:Ancient|Ancient|2}} {{2|Relics|Relic}}.\n\n== Sources ==\nAt the start of the run, can be offered by {{KW|Neow||2}}.\n\n== Update History ==\n*'''Early Access v0.103.2'''\n**Added Neow's Talisman to the game.\n*'''Early Access v0.100.0 (BETA)'''\n**Added Neow's Talisman to the game.\n\n[[Category:Relics]] [[Category:Slay the Spire 2 Content]]"
}