{
  "page": "Slay_the_Spire_2:Prismatic Gem",
  "short_name": "Prismatic Gem",
  "summary": "is an  . After you obtain this Relic, your card rewards will show cards from other colors excluding . Additionally, you gain  at the start of each turn.",
  "sections": {},
  "display_title": "<span class=\"mw-page-title-namespace\">Slay the Spire 2</span><span class=\"mw-page-title-separator\">:</span><span class=\"mw-page-title-main\">Prismatic Gem</span>",
  "fetched_at": "2026-05-20T06:21:32Z",
  "wikitext_chars": 2907,
  "wikitext": "{{Relic Infobox|Prismatic Gem|2}}{{R|Prismatic Gem||2}} is an {{QueryLink|Relics|rarity:Ancient|Ancient|2}} {{2|Relics|Relic}}. After you obtain this Relic, your card rewards will show cards from other colors excluding {{QueryLink|Cards|color:Colorless|Colorless Cards|2}}. Additionally, you gain {{Icon|CE|2}} at the start of each turn.\n\n==Sources==\nAfter fighting a {{2|Bosses|Boss}} in {{2|Acts|Act 1}}, it can be offered by {{KW|Orobas||2}}.\n\n===Spawn Restrictions===\n*Because '''Prismatic Gem''' shares a relic pool with {{R|Electric Shrymp||2}}, {{R|Glass Eye||2}}, {{R|Sand Castle||2}}, and {{R|Sea Glass||2}}, only 1 of the 5 can be offered by {{KW|Orobas||2}}.\n**'''Prismatic Gem''' is the least likely of these {{2|Relics}} to appear, with an ~8% chance of doing so.\n\n==Notes==\nWhen playing as any character except the {{2|Defect}}, you gain 1 {{2|Orbs#Orb_Slot|Orb Slot}} when you first play an {{2|Orbs|Orb}} card during combat\n\n==Interactions==\nSources of cards that are not card rewards, such as {{C|White Noise||2}} or potions which offer a choice of cards when used, will still only grant cards from your current character.\n<!-- Potential testing: What other events involve card rewards, and are they consistently affected by Prismatic Gem? -->\n===Neutral===\n*If the player encounters the {{E|Colorful Philosophers|2}} {{2|Event}}, and has '''Prismatic Gem''', then regardless of which character's card pool is chosen, the resulting card rewards will include cards from ''all'' the characters, including the current character.\n**If the player also has {{R|Dingy Rug||2}}, and Dingy Rug was picked up ''before'' Prismatic Gem, the resulting card rewards will include {{QueryLink|Cards|color:Colorless|Colorless}} cards in addition to cards of the chosen card pool- but not cards from additional characters.\n**If the player also has {{R|Dingy Rug||2}}, but Dingy Rug was picked up ''after'' Prismatic Gem, the resulting card rewards will include cards from ''all'' the characters, including the current character, but ''not'' include {{QueryLink|Cards|color:Colorless|Colorless}} cards.\n<!-- ^ This binary may apply to all events involving card rewards. -->\n*'''Prismatic Gem''' does not affect cards presented by [[Slay_the_Spire_2:The_Merchant|The Merchant]].\n**However if the Store {{2|Relic}} {{R|Orrery||2}} is purchased, the resulting card rewards ''will'' be affected by '''Prismatic Gem'''.\n====Relics====\n{{R|Dingy Rug||2}}: Colorless Cards also appear in card rewards\n\n== Trivia ==\n* The effect of this relic is similar to {{R|Prismatic Shard}} from the first Slay the Spire, however {{QueryLink|Cards|color:Colorless|Colorless Cards|2}} will not appear and an extra {{KW|Energy||2}} is given at the start of your turn.\n\n== Update History ==\n*'''Early Access v0.98'''\n**Added Prismatic Gem to the game.\n\n[[Category:Relics]] [[Category:Slay the Spire 2 Content]] [[Category:ToUpdate]]"
}